radb/RALexer.py
radb/RAParser.py
radb/RAParserVisitor.py
radb/__init__.py
radb/ast.py
radb/db.py
radb/parse.py
radb/ra.py
radb/sys.ini
radb/typesys.py
radb/utils.py
radb/views.py
radb-3.0.5.dist-info/LICENSE.txt
radb-3.0.5.dist-info/METADATA
radb-3.0.5.dist-info/WHEEL
radb-3.0.5.dist-info/entry_points.txt
radb-3.0.5.dist-info/top_level.txt
radb-3.0.5.dist-info/RECORD
