Metadata-Version: 2.1
Name: radb
Version: 3.0.5
Summary: A relational algebra interpreter over relational databases
Home-page: https://github.com/junyang/radb
Author: Jun Yang
Author-email: junyang@cs.duke.edu
License: MIT
Keywords: database relational algebra
Platform: UNKNOWN
Classifier: Development Status :: 4 - Beta
Classifier: Intended Audience :: Education
Classifier: Intended Audience :: Developers
Classifier: License :: OSI Approved :: MIT License
Classifier: Topic :: Database
Classifier: Topic :: Database :: Front-Ends
Classifier: Topic :: Software Development :: Interpreters
Classifier: Programming Language :: Python :: 3
Requires-Python: >=3.5
License-File: LICENSE.txt
Requires-Dist: SQLAlchemy (>=2.0)
Requires-Dist: antlr4-python3-runtime (>=4.12)
